{"variables":[],"info":{"name":"Laravel API","_postman_id":"70996404-9df9-4ffa-bd71-56dd8aae16d2","description":"","schema":"https:\/\/schema.getpostman.com\/json\/collection\/v2.0.0\/collection.json"},"item":[{"name":"Auth","description":"","item":[{"name":"Handle a login request to the application.","request":{"url":"http:\/\/api.darestreams.com\/login","method":"POST","body":{"mode":"formdata","formdata":[{"key":"email","value":"example@example.ru","type":"text","enabled":true},{"key":"password","value":"jadfohasd092","type":"text","enabled":true}]},"description":"","response":[]}},{"name":"Handle a registration request for the application.","request":{"url":"http:\/\/api.darestreams.com\/register","method":"POST","body":{"mode":"formdata","formdata":[{"key":"name","value":"Archibald","type":"text","enabled":true},{"key":"nickname","value":"Archi89","type":"text","enabled":true},{"key":"email","value":"example@example.ru","type":"text","enabled":true},{"key":"password","value":"jadfohasd092","type":"text","enabled":true},{"key":"lang","value":"ru","type":"text","enabled":true}]},"description":"","response":[]}},{"name":"Send a reset link to the given user.","request":{"url":"http:\/\/api.darestreams.com\/password\/email","method":"POST","body":{"mode":"formdata","formdata":[{"key":"email","value":"example@example.ru","type":"text","enabled":true}]},"description":"","response":[]}},{"name":"Reset the given user's password.","request":{"url":"http:\/\/api.darestreams.com\/password\/reset","method":"POST","body":{"mode":"formdata","formdata":[{"key":"token","value":"adnf981nsdvuohnlansdou1nj1","type":"text","enabled":true},{"key":"email","value":"example@example.ru","type":"text","enabled":true},{"key":"password","value":"jadfohasd092","type":"text","enabled":true},{"key":"password_confirmation","value":"jadfohasd092","type":"text","enabled":true}]},"description":"","response":[]}},{"name":"Redirect the user to the provider authentication page.","request":{"url":"http:\/\/api.darestreams.com\/oauth\/{driver}","method":"GET","body":{"mode":"formdata","formdata":[]},"description":"{driver} - social provider: facebook, twitch, youtube, steam, discord","response":[]}},{"name":"Obtain the user information from the provider.","request":{"url":"http:\/\/api.darestreams.com\/oauth\/{driver}\/callback","method":"GET","body":{"mode":"formdata","formdata":[]},"description":"{driver} - social provider: facebook, twitch, youtube, steam, discord","response":[]}},{"name":"Mark the user's email address as verified.","request":{"url":"http:\/\/api.darestreams.com\/email\/verify\/{user}","method":"POST","body":{"mode":"formdata","formdata":[]},"description":"{user} - integer id of user in database.","response":[]}},{"name":"Resend the email verification notification.","request":{"url":"http:\/\/api.darestreams.com\/email\/resend","method":"POST","body":{"mode":"formdata","formdata":[{"key":"email","value":"example@example.ru","type":"text","enabled":true}]},"description":"","response":[]}},{"name":"Log the user out of the application.","request":{"url":"http:\/\/api.darestreams.com\/logout","method":"POST","body":{"mode":"formdata","formdata":[]},"description":"","response":[]}}]},{"name":"Channels","description":"","item":[{"name":"Get top channels","request":{"url":"http:\/\/api.darestreams.com\/channels\/top","method":"GET","body":{"mode":"formdata","formdata":[]},"description":"","response":[]}},{"name":"Display a listing of the resource.","request":{"url":"http:\/\/api.darestreams.com\/channels","method":"GET","body":{"mode":"formdata","formdata":[]},"description":"","response":[]}},{"name":"Detail channel's info.","request":{"url":"http:\/\/api.darestreams.com\/channels\/{channel}","method":"GET","body":{"mode":"formdata","formdata":[]},"description":"","response":[]}},{"name":"Update info about channel.","request":{"url":"http:\/\/api.darestreams.com\/channels\/{channel}","method":"PUT","body":{"mode":"urlencoded","urlencoded":[{"key":"description","value":"Long description.","type":"text","enabled":true},{"key":"logo","value":"labore","type":"text","enabled":true},{"key":"game_id","value":7,"type":"text","enabled":true}]},"description":"","response":[]}}]},{"name":"Games","description":"","item":[{"name":"Top categories","request":{"url":"http:\/\/api.darestreams.com\/games\/top","method":"GET","body":{"mode":"formdata","formdata":[]},"description":"","response":[]}},{"name":"Display a listing of the resource.","request":{"url":"http:\/\/api.darestreams.com\/games","method":"GET","body":{"mode":"formdata","formdata":[]},"description":"","response":[]}},{"name":"Display the specified resource.","request":{"url":"http:\/\/api.darestreams.com\/games\/{game}","method":"GET","body":{"mode":"formdata","formdata":[]},"description":"","response":[]}},{"name":"Offer new category.","request":{"url":"http:\/\/api.darestreams.com\/games\/offer","method":"POST","body":{"mode":"formdata","formdata":[{"key":"title","value":"New category.","type":"text","enabled":true}]},"description":"","response":[]}}]},{"name":"Streams","description":"","item":[{"name":"Display a listing of the resource.","request":{"url":"http:\/\/api.darestreams.com\/streams","method":"GET","body":{"mode":"formdata","formdata":[]},"description":"","response":[]}},{"name":"Create new stream.","request":{"url":"http:\/\/api.darestreams.com\/streams","method":"POST","body":{"mode":"formdata","formdata":[{"key":"game_id","value":7,"type":"text","enabled":true},{"key":"link","value":"inventore","type":"text","enabled":true},{"key":"start_at","value":"quidem","type":"text","enabled":true},{"key":"tags","value":"velit","type":"text","enabled":true}]},"description":"","response":[]}},{"name":"Display the specified resource.","request":{"url":"http:\/\/api.darestreams.com\/streams\/{stream}","method":"GET","body":{"mode":"formdata","formdata":[]},"description":"","response":[]}},{"name":"Update stream.","request":{"url":"http:\/\/api.darestreams.com\/streams\/{stream}","method":"PUT","body":{"mode":"urlencoded","urlencoded":[{"key":"game_id","value":4,"type":"text","enabled":true},{"key":"link","value":"nostrum","type":"text","enabled":true},{"key":"start_at","value":"amet","type":"text","enabled":true},{"key":"tags","value":"accusamus","type":"text","enabled":true}]},"description":"Update before starting of the stream.","response":[]}},{"name":"Get stream's chat info.","request":{"url":"http:\/\/api.darestreams.com\/streams\/{stream}\/thread","method":"GET","body":{"mode":"formdata","formdata":[]},"description":"","response":[]}}]},{"name":"Streams tasks","description":"","item":[{"name":"Display a listing of the resource.","request":{"url":"http:\/\/api.darestreams.com\/streams\/{stream}\/tasks","method":"GET","body":{"mode":"formdata","formdata":[]},"description":"{stream} - stream integer id.","response":[]}},{"name":"Create new task for stream.","request":{"url":"http:\/\/api.darestreams.com\/streams\/{stream}\/tasks","method":"POST","body":{"mode":"formdata","formdata":[{"key":"small_text","value":"aut","type":"text","enabled":true},{"key":"full_text","value":"praesentium","type":"text","enabled":true},{"key":"interval_time","value":2,"type":"text","enabled":true},{"key":"min_amount","value":18,"type":"text","enabled":true},{"key":"is_superbowl","value":true,"type":"text","enabled":true},{"key":"min_amount_superbowl","value":1,"type":"text","enabled":true},{"key":"tags","value":"hic","type":"text","enabled":true}]},"description":"{stream} - stream integer id.","response":[]}},{"name":"Display the specified resource.","request":{"url":"http:\/\/api.darestreams.com\/streams\/{stream}\/tasks\/{task}","method":"GET","body":{"mode":"formdata","formdata":[]},"description":"{stream} - stream integer id.\n{$task} - $task integer id.","response":[]}},{"name":"Update task for stream.","request":{"url":"http:\/\/api.darestreams.com\/streams\/{stream}\/tasks\/{task}","method":"PUT","body":{"mode":"urlencoded","urlencoded":[{"key":"small_text","value":"voluptas","type":"text","enabled":true},{"key":"full_text","value":"excepturi","type":"text","enabled":true},{"key":"interval_time","value":4,"type":"text","enabled":true},{"key":"min_amount","value":10,"type":"text","enabled":true},{"key":"is_superbowl","value":false,"type":"text","enabled":true},{"key":"min_amount_superbowl","value":7,"type":"text","enabled":true},{"key":"tags","value":"quisquam","type":"text","enabled":true}]},"description":"{stream} - stream integer id.\n{task} - task integer id.","response":[]}}]},{"name":"Streams tasks donations","description":"","item":[{"name":"List of task's donations.","request":{"url":"http:\/\/api.darestreams.com\/streams\/{stream}\/tasks\/{task}\/transactions","method":"GET","body":{"mode":"formdata","formdata":[]},"description":"{stream} - stream integer id.\n{task} - task integer id.","response":[]}},{"name":"Create new task for stream.","request":{"url":"http:\/\/api.darestreams.com\/streams\/{stream}\/tasks\/{task}\/transactions","method":"POST","body":{"mode":"formdata","formdata":[{"key":"amount","value":13,"type":"text","enabled":true}]},"description":"{stream} - stream integer id.","response":[]}},{"name":"Detail donations of task.","request":{"url":"http:\/\/api.darestreams.com\/streams\/{stream}\/tasks\/{task}\/transactions\/{transaction}","method":"GET","body":{"mode":"formdata","formdata":[]},"description":"{stream} - stream integer id.\n{task} - task integer id.\n{transaction} - transaction integer id.","response":[]}}]},{"name":"Streams tasks votes","description":"","item":[{"name":"http:\/\/api.darestreams.com\/streams\/{stream}\/tasks\/{task}\/votes","request":{"url":"http:\/\/api.darestreams.com\/streams\/{stream}\/tasks\/{task}\/votes","method":"POST","body":{"mode":"formdata","formdata":[]},"description":"","response":[]}}]},{"name":"Threads","description":"","item":[{"name":"Display a listing of the resource.","request":{"url":"http:\/\/api.darestreams.com\/threads","method":"GET","body":{"mode":"formdata","formdata":[]},"description":"","response":[]}},{"name":"Display the specified resource.","request":{"url":"http:\/\/api.darestreams.com\/threads\/{thread}","method":"GET","body":{"mode":"formdata","formdata":[]},"description":"","response":[]}}]},{"name":"Threads messages","description":"","item":[{"name":"Get messages of thread.","request":{"url":"http:\/\/api.darestreams.com\/threads\/{thread}\/messages","method":"GET","body":{"mode":"formdata","formdata":[]},"description":"","response":[]}},{"name":"Create new message for thread.","request":{"url":"http:\/\/api.darestreams.com\/threads\/{thread}\/messages","method":"POST","body":{"mode":"formdata","formdata":[{"key":"body","value":"voluptas","type":"text","enabled":true}]},"description":"","response":[]}},{"name":"Detail message of thread.","request":{"url":"http:\/\/api.darestreams.com\/threads\/{thread}\/messages\/{message}","method":"GET","body":{"mode":"formdata","formdata":[]},"description":"{thread} - thread integer id.","response":[]}},{"name":"Update message.","request":{"url":"http:\/\/api.darestreams.com\/threads\/{thread}\/messages\/{message}","method":"PUT","body":{"mode":"urlencoded","urlencoded":[]},"description":"","response":[]}}]},{"name":"Threads participants","description":"","item":[{"name":"Get participant users of the chat.","request":{"url":"http:\/\/api.darestreams.com\/threads\/{thread}\/participants","method":"GET","body":{"mode":"formdata","formdata":[]},"description":"","response":[]}}]},{"name":"Users","description":"","item":[{"name":"Get authorized user.","request":{"url":"http:\/\/api.darestreams.com\/users\/me","method":"GET","body":{"mode":"formdata","formdata":[]},"description":"","response":[]}},{"name":"Display a listing of the resource.","request":{"url":"http:\/\/api.darestreams.com\/users","method":"GET","body":{"mode":"formdata","formdata":[]},"description":"","response":[]}},{"name":"Display the specified resource.","request":{"url":"http:\/\/api.darestreams.com\/users\/{user}","method":"GET","body":{"mode":"formdata","formdata":[]},"description":"","response":[]}},{"name":"Update user fields.","request":{"url":"http:\/\/api.darestreams.com\/users\/{user}","method":"PUT","body":{"mode":"urlencoded","urlencoded":[{"key":"name","value":"Archibald","type":"text","enabled":true},{"key":"last_name","value":"maiores","type":"text","enabled":true},{"key":"middle_name","value":"error","type":"text","enabled":true},{"key":"nickname","value":"Archi89","type":"text","enabled":true},{"key":"email","value":"example@example.ru","type":"text","enabled":true}]},"description":"","response":[]}},{"name":"User's account\n{user} - user id integer.","request":{"url":"http:\/\/api.darestreams.com\/users\/{user}\/account","method":"GET","body":{"mode":"formdata","formdata":[]},"description":"","response":[]}},{"name":"User's channel\n{user} - user id integer.","request":{"url":"http:\/\/api.darestreams.com\/users\/{user}\/channel","method":"GET","body":{"mode":"formdata","formdata":[]},"description":"","response":[]}},{"name":"Update user's avatar","request":{"url":"http:\/\/api.darestreams.com\/users\/{user}\/avatar","method":"PATCH","body":{"mode":"formdata","formdata":[]},"description":"","response":[]}},{"name":"Update user's overlay.","request":{"url":"http:\/\/api.darestreams.com\/users\/{user}\/overlay","method":"PATCH","body":{"mode":"formdata","formdata":[]},"description":"","response":[]}},{"name":"Update user's password.","request":{"url":"http:\/\/api.darestreams.com\/users\/{user}\/password","method":"PATCH","body":{"mode":"formdata","formdata":[{"key":"password","value":"jadfohasd092","type":"text","enabled":true}]},"description":"","response":[]}},{"name":"Follow the user.","request":{"url":"http:\/\/api.darestreams.com\/users\/{user}\/follow","method":"POST","body":{"mode":"formdata","formdata":[]},"description":"{user} - user id you want follow for.","response":[]}},{"name":"Unfollow the user.","request":{"url":"http:\/\/api.darestreams.com\/users\/{user}\/unfollow","method":"PATCH","body":{"mode":"formdata","formdata":[]},"description":"{user} - user id you want unfollow.","response":[]}},{"name":"User's followers","request":{"url":"http:\/\/api.darestreams.com\/users\/{user}\/followers","method":"GET","body":{"mode":"formdata","formdata":[]},"description":"{user} - user id you want follow for.","response":[]}},{"name":"Users followings\n{user} - user id integer.","request":{"url":"http:\/\/api.darestreams.com\/users\/{user}\/followings","method":"GET","body":{"mode":"formdata","formdata":[]},"description":"","response":[]}}]},{"name":"Users notifications","description":"","item":[{"name":"http:\/\/api.darestreams.com\/users\/{user}\/notifications\/unread","request":{"url":"http:\/\/api.darestreams.com\/users\/{user}\/notifications\/unread","method":"GET","body":{"mode":"formdata","formdata":[]},"description":"","response":[]}},{"name":"http:\/\/api.darestreams.com\/users\/{user}\/notifications\/setReadAll","request":{"url":"http:\/\/api.darestreams.com\/users\/{user}\/notifications\/setReadAll","method":"PATCH","body":{"mode":"formdata","formdata":[]},"description":"","response":[]}},{"name":"http:\/\/api.darestreams.com\/users\/{user}\/notifications","request":{"url":"http:\/\/api.darestreams.com\/users\/{user}\/notifications","method":"GET","body":{"mode":"formdata","formdata":[]},"description":"","response":[]}},{"name":"Display the specified resource.","request":{"url":"http:\/\/api.darestreams.com\/users\/{user}\/notifications\/{notification}","method":"GET","body":{"mode":"formdata","formdata":[]},"description":"","response":[]}},{"name":"http:\/\/api.darestreams.com\/users\/{user}\/notifications\/{notification}\/setRead","request":{"url":"http:\/\/api.darestreams.com\/users\/{user}\/notifications\/{notification}\/setRead","method":"PATCH","body":{"mode":"formdata","formdata":[]},"description":"","response":[]}}]},{"name":"Users oauth accounts","description":"","item":[{"name":"Display a listing of the resource.","request":{"url":"http:\/\/api.darestreams.com\/users\/{user}\/oauthproviders","method":"GET","body":{"mode":"formdata","formdata":[]},"description":"","response":[]}},{"name":"http:\/\/api.darestreams.com\/users\/{user}\/oauthproviders\/{oauthprovider}","request":{"url":"http:\/\/api.darestreams.com\/users\/{user}\/oauthproviders\/{oauthprovider}","method":"GET","body":{"mode":"formdata","formdata":[]},"description":"","response":[]}}]},{"name":"Users transactions","description":"","item":[{"name":"Display a listing of the resource.","request":{"url":"http:\/\/api.darestreams.com\/users\/{user}\/transactions","method":"GET","body":{"mode":"formdata","formdata":[]},"description":"","response":[]}},{"name":"Display the specified resource.","request":{"url":"http:\/\/api.darestreams.com\/users\/{user}\/transactions\/{transaction}","method":"GET","body":{"mode":"formdata","formdata":[]},"description":"","response":[]}}]},{"name":"Votes","description":"","item":[{"name":"Display a listing of the resource.","request":{"url":"http:\/\/api.darestreams.com\/votes","method":"GET","body":{"mode":"formdata","formdata":[]},"description":"","response":[]}},{"name":"Display the specified resource.","request":{"url":"http:\/\/api.darestreams.com\/votes\/{vote}","method":"GET","body":{"mode":"formdata","formdata":[]},"description":"","response":[]}},{"name":"http:\/\/api.darestreams.com\/votes\/{vote}","request":{"url":"http:\/\/api.darestreams.com\/votes\/{vote}","method":"PUT","body":{"mode":"urlencoded","urlencoded":[]},"description":"","response":[]}}]}]}